digitaldatai/__init__.py
digitaldatai/common.py
digitaldatai/digitaldatai.py
digitaldatai-0.0.1.dist-info/LICENSE
digitaldatai-0.0.1.dist-info/METADATA
digitaldatai-0.0.1.dist-info/WHEEL
digitaldatai-0.0.1.dist-info/entry_points.txt
digitaldatai-0.0.1.dist-info/top_level.txt
digitaldatai-0.0.1.dist-info/RECORD
